expecto/__init__.py
expecto/core.py
expecto/version.py
expecto/data/README.rst
expecto/tests/__init__.py
expecto/tests/test_core.py
expecto-0.1.4.dist-info/LICENSE.rst
expecto-0.1.4.dist-info/METADATA
expecto-0.1.4.dist-info/WHEEL
expecto-0.1.4.dist-info/top_level.txt
expecto-0.1.4.dist-info/RECORD
