Metadata-Version: 2.2
Name: expecto
Version: 0.1.4
Summary: PHOENIX model spectrum retriever
Home-page: https://github.com/bmorris3/expecto
Author: Brett M. Morris
Author-email: morrisbrettm@gmail.com
License: BSD 3-Clause
Requires-Python: >=3.5
License-File: licenses/LICENSE.rst
Requires-Dist: astropy
Requires-Dist: specutils
Requires-Dist: numpy
Provides-Extra: all
Provides-Extra: test
Requires-Dist: pytest; extra == "test"
Requires-Dist: pytest-doctestplus; extra == "test"
Requires-Dist: pytest-cov; extra == "test"
Requires-Dist: pytest-remotedata; extra == "test"
Provides-Extra: docs
Requires-Dist: sphinx; extra == "docs"
Requires-Dist: sphinx-automodapi; extra == "docs"
Requires-Dist: matplotlib; extra == "docs"
Requires-Dist: sphinx-book-theme>=0.3.3; extra == "docs"
Requires-Dist: numpydoc; extra == "docs"
